smartcontext/backends.py
smartcontext/context.py
smartcontext/memory.py
smartcontext/utils.py
smart_context-0.0.10.dist-info/LICENSE
smart_context-0.0.10.dist-info/METADATA
smart_context-0.0.10.dist-info/WHEEL
smart_context-0.0.10.dist-info/top_level.txt
smart_context-0.0.10.dist-info/RECORD
