Metadata-Version: 2.1
Name: smart-context
Version: 0.0.10
Summary: Large Language Models Tools
Author-email: Vladimir Petrukhin <man4j@ya.ru>
Project-URL: Homepage, https://github.com/Equiron-AI/smart-context
Classifier: Development Status :: 4 - Beta
Classifier: Programming Language :: Python :: 3.10
Classifier: Programming Language :: Python :: 3.11
Classifier: License :: OSI Approved :: MIT License
Classifier: Operating System :: OS Independent
Requires-Python: >=3.10
License-File: LICENSE
Requires-Dist: transformers>=4.44.2
Requires-Dist: jinja2>=3.1.4
Requires-Dist: sseclient-py
Requires-Dist: pytz
